[
  {
    "completed_pages": 4,
    "job_name": "hourly",
    "progress_pct": 100.0,
    "status": "COMPLETED",
    "total_pages": 4,
    "updated_at": "2026-07-21T15:07:17.842579+09:00"
  },
  {
    "completed_pages": 1,
    "job_name": "kma_hourly",
    "progress_pct": 100.0,
    "status": "COMPLETED",
    "total_pages": 1,
    "updated_at": "2026-07-21T15:07:18.774837+09:00"
  },
  {
    "completed_pages": 1,
    "job_name": "daily",
    "progress_pct": 100.0,
    "status": "COMPLETED",
    "total_pages": 1,
    "updated_at": "2026-07-21T12:12:46.039615+09:00"
  },
  {
    "completed_pages": 1,
    "job_name": "kma_daily",
    "progress_pct": 100.0,
    "status": "COMPLETED",
    "total_pages": 1,
    "updated_at": "2026-07-21T12:12:47.094581+09:00"
  },
  {
    "completed_pages": 4,
    "job_name": "monthly",
    "progress_pct": 100.0,
    "status": "COMPLETED",
    "total_pages": 4,
    "updated_at": "2026-07-20T23:30:53.778810+09:00"
  }
]