{
  "daily": {
    "first_collected": "2026-07-08T18:10:44.089454+09:00",
    "last_collected": "2026-07-17T08:13:37.968369+09:00",
    "total_records": 795
  },
  "hourly": {
    "first_collected": "2026-07-08T18:09:45.473923+09:00",
    "last_collected": "2026-07-17T08:02:46.059608+09:00",
    "total_records": 17514
  },
  "kma_daily": {
    "first_collected": "2026-07-08T18:10:45.208946+09:00",
    "last_collected": "2026-07-17T08:13:39.043381+09:00",
    "total_records": 52
  },
  "kma_hourly": {
    "first_collected": "2026-07-08T18:10:34.086373+09:00",
    "last_collected": "2026-07-17T08:02:51.298710+09:00",
    "total_records": 206
  },
  "monthly": {
    "first_collected": "2026-07-08T18:10:46.091954+09:00",
    "last_collected": "2026-07-16T23:30:00.431003+09:00",
    "total_records": 910
  },
  "total": {
    "first_collected": "2026-07-08T18:09:45.473923+09:00",
    "last_collected": "2026-07-17T08:13:39.043381+09:00",
    "total_records": 19477
  }
}